etsy2/__init__.py
etsy2/_core.py
etsy2/_v2.py
etsy2/etsy_env.py
etsy2/oauth.py
etsy2-0.7.0.dist-info/COPYING
etsy2-0.7.0.dist-info/METADATA
etsy2-0.7.0.dist-info/WHEEL
etsy2-0.7.0.dist-info/top_level.txt
etsy2-0.7.0.dist-info/RECORD
