Metadata-Version: 2.1
Name: etsy2
Version: 0.7.0
Summary: Python access to the Etsy API
Home-page: UNKNOWN
Author: Sean Scheetz
Author-email: contact_through_github@gmail.com
License: GPL v3
Project-URL: Source Code, https://github.com/sscheetz/etsy-python2
Keywords: etsy api handmade
Platform: UNKNOWN
